neobase/__init__.py
neobase/__main__.py
neobase/_version.py
neobase/neobase.py
neobase/optd_por_public.csv
neobase-0.34.21.dist-info/licenses/LICENSE
neobase-0.34.21.dist-info/METADATA
neobase-0.34.21.dist-info/WHEEL
neobase-0.34.21.dist-info/entry_points.txt
neobase-0.34.21.dist-info/top_level.txt
neobase-0.34.21.dist-info/RECORD
