Metadata-Version: 2.4
Name: NeoBase
Version: 0.34.21
Summary: Python library to manipulate Open Travel Data
Home-page: https://github.com/alexprengere/neobase
Author: Alex Prengère
Author-email: alex.prengere@gmail.com
Classifier: Development Status :: 5 - Production/Stable
Classifier: Programming Language :: Python :: 3
Classifier: Programming Language :: Python :: 3 :: Only
Classifier: Programming Language :: Python :: Implementation :: CPython
Classifier: Programming Language :: Python :: Implementation :: PyPy
Requires-Python: >=3.9
License-File: LICENSE
Dynamic: license-file
